astro_extras/__init__.py
astro_extras/hooks/__init__.py
astro_extras/operators/__init__.py
astro_extras/operators/direct.py
astro_extras/operators/session.py
astro_extras/operators/table.py
astro_extras/sensors/__init__.py
astro_extras/sensors/auto.py
astro_extras/sensors/file.py
astro_extras/templates/session_close.sql
astro_extras/templates/session_open.sql
astro_extras/templates/table_actuals_select.sql
astro_extras/templates/table_actuals_select_delta.sql
astro_extras/templates/table_timed_update.sql
astro_extras/templates/table_transfer_nosess.sql
astro_extras/templates/table_transfer_sess.sql
astro_extras/utils/__init__.py
astro_extras/utils/data_compare.py
astro_extras/utils/datetime_local.py
astro_extras/utils/postgres_sql.py
astro_extras/utils/template.py
astro_extras/utils/utils.py
astro_extras-0.2.2.dist-info/LICENSE
astro_extras-0.2.2.dist-info/METADATA
astro_extras-0.2.2.dist-info/WHEEL
astro_extras-0.2.2.dist-info/top_level.txt
astro_extras-0.2.2.dist-info/RECORD
