Metadata-Version: 2.2
Name: astro_extras
Version: 0.2.2
Summary: Additional Astro SDK operators
Home-page: https://github.com/skolchin/astro-extras
Author: Kol
Author-email: skolchin@gmail.com
Classifier: Programming Language :: Python :: 3
Classifier: Operating System :: OS Independent
Classifier: Framework :: Apache Airflow
Classifier: Framework :: Apache Airflow :: Provider
Requires-Python: >=3.10
License-File: LICENSE
Requires-Dist: apache-airflow[pandas,postgres]>=2.7.0
Requires-Dist: astro-sdk-python[postgres]==1.8.1
Requires-Dist: apache-airflow-providers-openlineage>=1.8.0
Requires-Dist: openpyxl>=3.0.0
Requires-Dist: python-dateutil>=2.8.0
Dynamic: author
Dynamic: author-email
Dynamic: classifier
Dynamic: description
Dynamic: description-content-type
Dynamic: home-page
Dynamic: requires-dist
Dynamic: requires-python
Dynamic: summary
